odoo/addons/pos_fixed_discount/README.rst
odoo/addons/pos_fixed_discount/__init__.py
odoo/addons/pos_fixed_discount/__manifest__.py
odoo/addons/pos_fixed_discount/i18n/es.po
odoo/addons/pos_fixed_discount/i18n/it.po
odoo/addons/pos_fixed_discount/i18n/pos_fixed_discount.pot
odoo/addons/pos_fixed_discount/readme/CONTRIBUTORS.rst
odoo/addons/pos_fixed_discount/readme/DESCRIPTION.rst
odoo/addons/pos_fixed_discount/readme/USAGE.rst
odoo/addons/pos_fixed_discount/static/description/icon.png
odoo/addons/pos_fixed_discount/static/description/index.html
odoo/addons/pos_fixed_discount/static/src/js/FixedDiscountButton.js
odoo/addons/pos_fixed_discount/static/src/xml/discount_templates.xml
odoo_addon_pos_fixed_discount-15.0.1.0.1.4.dist-info/METADATA
odoo_addon_pos_fixed_discount-15.0.1.0.1.4.dist-info/WHEEL
odoo_addon_pos_fixed_discount-15.0.1.0.1.4.dist-info/top_level.txt
odoo_addon_pos_fixed_discount-15.0.1.0.1.4.dist-info/RECORD
