Metadata-Version: 2.1
Name: odoo-addon-pos-fixed-discount
Version: 15.0.1.0.1.4
Summary: Allow to apply discounts with fixed amount
Home-page: https://github.com/OCA/pos
Author: TAKOBI, Odoo Community Association (OCA)
Author-email: support@odoo-community.org
License: LGPL-3
Platform: UNKNOWN
Classifier: Programming Language :: Python
Classifier: Framework :: Odoo
Classifier: Framework :: Odoo :: 15.0
Classifier: License :: OSI Approved :: GNU Lesser General Public License v3 (LGPLv3)
Classifier: Development Status :: 4 - Beta
Requires-Python: >=3.8
Requires-Dist: odoo <15.1dev,>=15.0a
